blpapipd/__init__.py
blpapipd/blpapipd.py
blpapipd/plot_utilities.py
blpapipd/plot_voltron.py
blpapipd-0.2.1.dist-info/LICENSE
blpapipd-0.2.1.dist-info/METADATA
blpapipd-0.2.1.dist-info/WHEEL
blpapipd-0.2.1.dist-info/top_level.txt
blpapipd-0.2.1.dist-info/RECORD
