Metadata-Version: 2.1
Name: blpapipd
Version: 0.2.1
Summary: Extract Bloomberg (BBG) data into pandas timeseries object w/ caching.  Leverages blpapi desktop api in Python
Home-page: https://github.com/tnicolas/blpapipd
Author: T. Nicolas Steinbach
Author-email: t@steinbachs.us
Project-URL: Bug Tracker, https://github.com/tnicolas/blpapipd/issues
Classifier: Programming Language :: Python :: 3
Classifier: License :: OSI Approved :: MIT License
Classifier: Operating System :: Microsoft :: Windows :: Windows 10
Requires-Python: >=3.6
License-File: LICENSE
